MANIFEST.in
setup.py
ComRec/__init__.py
ComRec/apply.py
ComRec/data.py
ComRec/model.py
ComRec/utils.py
ComRec/data_path/region.txt
ComRec/data_path/test_data
ComRec/data_path/train_data
ComRec/data_path/word2id_1.pkl
ComRec/data_path/word2id_list
ComRec/data_path/word2id_tecent.pkl
ComRec/data_path/word2id_tecent_embedding
ComRec/data_path/word_npy
ComRec/data_tools/__init__.py
ComRec/data_tools/company_name_bio.py
ComRec/data_tools/region_bio.py
ComRec/data_tools/word2id_pkl.py
ComRec/result_path/1548988896/checkpoints/checkpoint
ComRec/result_path/1548988896/checkpoints/model-2840.data-00000-of-00001
ComRec/result_path/1548988896/checkpoints/model-2840.index
ComRec/result_path/1548988896/checkpoints/model-2840.meta
ComRec/result_path/1548988896/results/label_1
ComRec/result_path/1548988896/results/label_10
ComRec/result_path/1548988896/results/label_11
ComRec/result_path/1548988896/results/label_12
ComRec/result_path/1548988896/results/label_13
ComRec/result_path/1548988896/results/label_14
ComRec/result_path/1548988896/results/label_15
ComRec/result_path/1548988896/results/label_16
ComRec/result_path/1548988896/results/label_17
ComRec/result_path/1548988896/results/label_18
ComRec/result_path/1548988896/results/label_19
ComRec/result_path/1548988896/results/label_2
ComRec/result_path/1548988896/results/label_20
ComRec/result_path/1548988896/results/label_3
ComRec/result_path/1548988896/results/label_4
ComRec/result_path/1548988896/results/label_5
ComRec/result_path/1548988896/results/label_6
ComRec/result_path/1548988896/results/label_7
ComRec/result_path/1548988896/results/label_8
ComRec/result_path/1548988896/results/label_9
ComRec/result_path/1548988896/results/log.txt
ComRec/result_path/1548988896/results/result_metric_1
ComRec/result_path/1548988896/results/result_metric_10
ComRec/result_path/1548988896/results/result_metric_11
ComRec/result_path/1548988896/results/result_metric_12
ComRec/result_path/1548988896/results/result_metric_13
fuyun_ComRec.egg-info/PKG-INFO
fuyun_ComRec.egg-info/SOURCES.txt
fuyun_ComRec.egg-info/dependency_links.txt
fuyun_ComRec.egg-info/requires.txt
fuyun_ComRec.egg-info/top_level.txt